network_config/README.md
network_config/abis/erc20.json
network_config/abis/market.json
network_config/abis/router.json
network_config/abitrum_goerli/network.yaml
network_config/arbitrum_one/network.yaml
network_config/base/network.yaml
network_config/optimism/network.yaml
network_config/optimism_goerli/network.yaml
network_config/polygon_mumbai/network.yaml
rubi/__init__.py
rubi/client.py
rubi/contracts/__init__.py
rubi/contracts/base_contract.py
rubi/contracts/contract_types/__init__.py
rubi/contracts/contract_types/events.py
rubi/contracts/contract_types/transaction_receipt.py
rubi/contracts/erc20.py
rubi/contracts/market.py
rubi/contracts/router.py
rubi/contracts/transaction_handler.py
rubi/data/README.md
rubi/data/__init__.py
rubi/data/helpers/__init__.py
rubi/data/helpers/query_types.py
rubi/data/helpers/validation.py
rubi/data/market.py
rubi/network/__init__.py
rubi/network/network.py
rubi/order_tracking_client.py
rubi/rubicon_types/__init__.py
rubi/rubicon_types/erc20_transactions.py
rubi/rubicon_types/orderbook.py
rubi/rubicon_types/orders.py
rubi-3.0.0.dist-info/LICENSE
rubi-3.0.0.dist-info/METADATA
rubi-3.0.0.dist-info/WHEEL
rubi-3.0.0.dist-info/entry_points.txt
rubi-3.0.0.dist-info/RECORD
