Metadata-Version: 2.1
Name: rubi
Version: 3.0.0
Summary: A python SDK for the Rubicon Protocol
Author: denver
Author-email: denver@rubicon.finance
Requires-Python: >=3.10,<4.0
Classifier: Programming Language :: Python :: 3
Classifier: Programming Language :: Python :: 3.10
Classifier: Programming Language :: Python :: 3.11
Provides-Extra: docs
Requires-Dist: attributedict (==0.3.0)
Requires-Dist: black (==23.7.0)
Requires-Dist: eth-abi (==4.1.0)
Requires-Dist: eth-tester (==0.9.1b1)
Requires-Dist: eth-utils (==2.2.0)
Requires-Dist: hexbytes (==0.3.1)
Requires-Dist: py-evm (==0.7.0a4)
Requires-Dist: pytest (==7.4.0)
Requires-Dist: python-semantic-release (==7.34.3)
Requires-Dist: pyyaml (==6.0.1)
Requires-Dist: sphinx (==7.1.2) ; extra == "docs"
Requires-Dist: subgrounds[dash] (==1.6.1)
Requires-Dist: web3 (==6.8.0)
